pdf2ebook/__init__.py
pdf2ebook/base_page.py
pdf2ebook/base_pdf.py
pdf2ebook/constants.py
pdf2ebook/html_page.py
pdf2ebook/htmlex_pdf.py
pdf2ebook/logging.py
pdf2ebook/pages.py
pdf2ebook/pdf.py
pdf2ebook/text_page.py
pdf2ebook/utils.py
pdf2ebook/w2n.py
pdf2ebook/bin/__init__.py
pdf2ebook/bin/convert.py
pdf2ebook-2.3.0.dist-info/LICENSE
pdf2ebook-2.3.0.dist-info/METADATA
pdf2ebook-2.3.0.dist-info/WHEEL
pdf2ebook-2.3.0.dist-info/entry_points.txt
pdf2ebook-2.3.0.dist-info/top_level.txt
pdf2ebook-2.3.0.dist-info/RECORD
